Metadata-Version: 1.1
Name: painter-tk
Version: 1.5.0
Summary: 使用tkinter的Canvas控件制作的画板程序, 支持绘制矢量图, 用列表存储图像数据。
Home-page: https://github.com/qfcy/Python/tree/main/painter
Author: 七分诚意 qq:3076711200
Author-email: 3076711200@qq.com
License: UNKNOWN
Keywords: simple,text,editor,notepad,tkinter
Platform: UNKNOWN
Classifier: Programming Language :: Python
Classifier: Natural Language :: Chinese (Simplified)
Classifier: Topic :: Multimedia :: Graphics
Classifier: Topic :: Desktop Environment
Classifier: Topic :: Software Development :: User Interfaces
